MVDataProcessing/Clean.py
MVDataProcessing/Example.py
MVDataProcessing/Fill.py
MVDataProcessing/Util.py
MVDataProcessing/__init__.py
mvdataprocessing-0.1.12.dist-info/licenses/LICENSE
mvdataprocessing-0.1.12.dist-info/METADATA
mvdataprocessing-0.1.12.dist-info/WHEEL
mvdataprocessing-0.1.12.dist-info/top_level.txt
mvdataprocessing-0.1.12.dist-info/RECORD
