Metadata-Version: 2.4
Name: MVDataProcessing
Version: 0.1.12
Summary: Missing Data Imputation Method for Medium Voltage Distribution Network Feeders
Home-page: https://github.com/JMBacalhau/MVDataProcessing
Author: João Bacalhau
Author-email: joaomarcusbacalhau@gmail.com
Project-URL: Bug Tracker, https://github.com/JMBacalhau/MVDataProcessing/issues
Project-URL: Documentation, https://mvdataprocessing.readthedocs.io/en/latest/
Classifier: Programming Language :: Python :: 3
Classifier: Programming Language :: Python :: 3.9
Classifier: Programming Language :: Python :: 3.10
Classifier: Programming Language :: Python :: 3.11
Classifier: Programming Language :: Python :: 3.12
Classifier: License :: OSI Approved :: MIT License
Classifier: Operating System :: OS Independent
Requires-Python: >=3.9
License-File: LICENSE
Requires-Dist: pandas>=2.0.0
Requires-Dist: numpy>=1.24.0
Requires-Dist: matplotlib>=3.7.0
Dynamic: license-file
